[{"name":"render_template.action_view","payload":{"identifier":"/Users/billrashid/RubymineProjects/rotten-potatoes/rotten-potatoes/app/views/sessions/new.html.haml","layout":"layouts/application"},"time":"2016-09-26T10:26:14.124-05:00","transaction_id":"82a03310f93497c6d77a","end":"2016-09-26T10:26:14.126-05:00","children":[],"duration":1.381},{"name":"process_action.action_controller","payload":{"controller":"SessionsController","action":"new","params":{"controller":"sessions","action":"new"},"format":"html","method":"GET","path":"/login","status":200,"view_runtime":17.498814006103203,"db_runtime":0},"time":"2016-09-26T10:26:14.119-05:00","transaction_id":"82a03310f93497c6d77a","end":"2016-09-26T10:26:14.137-05:00","children":[],"duration":18.103}]